{"cameraMode":{"drawMode":0,"name":"Shaded","section":"Shading Mode"},"sceneLighting":true,"audioPlay":false,"sceneViewState":{"m_AlwaysRefresh":false,"showFog":true,"showSkybox":true,"showFlares":true,"showImageEffects":true,"showParticleSystems":true,"showVisualEffectGraphs":true,"m_FxEnabled":true},"in2DMode":false,"pivot":{"x":-94.45076751708985,"y":3.7021970748901369,"z":-35.0006103515625},"rotation":{"x":-0.043061789125204089,"y":0.9516250491142273,"z":-0.15728679299354554,"w":-0.26030904054641726},"size":10.47874641418457,"orthographic":false}